django_setup_configuration/__init__.py
django_setup_configuration/apps.py
django_setup_configuration/configuration.py
django_setup_configuration/exceptions.py
django_setup_configuration/fields.py
django_setup_configuration/model_utils.py
django_setup_configuration/models.py
django_setup_configuration/py.typed
django_setup_configuration/runner.py
django_setup_configuration/test_utils.py
django_setup_configuration/contrib/__init__.py
django_setup_configuration/contrib/auth/__init__.py
django_setup_configuration/contrib/auth/models.py
django_setup_configuration/contrib/auth/steps.py
django_setup_configuration/contrib/sites/__init__.py
django_setup_configuration/contrib/sites/models.py
django_setup_configuration/contrib/sites/steps.py
django_setup_configuration/documentation/__init__.py
django_setup_configuration/documentation/setup_config_example.py
django_setup_configuration/documentation/setup_config_usage.py
django_setup_configuration/documentation/templates/config_doc.rst
django_setup_configuration/management/__init__.py
django_setup_configuration/management/commands/__init__.py
django_setup_configuration/management/commands/setup_configuration.py
django_setup_configuration-0.11.0.dist-info/licenses/LICENSE
django_setup_configuration-0.11.0.dist-info/METADATA
django_setup_configuration-0.11.0.dist-info/WHEEL
django_setup_configuration-0.11.0.dist-info/top_level.txt
django_setup_configuration-0.11.0.dist-info/RECORD
