Metadata-Version: 2.4
Name: django_setup_configuration
Version: 0.11.0
Summary: Pluggable configuration setup used with the django management command
Author-email: Maykin Media <support@maykinmedia.nl>
License: Copyright 2024 Maykin Media
Project-URL: Homepage, https://github.com/maykinmedia/django-setup-configuration
Project-URL: Documentation, http://django-setup-configuration.readthedocs.io/en/latest/
Project-URL: Bug Tracker, https://github.com/maykinmedia/django-setup-configuration/issues
Project-URL: Source Code, https://github.com/maykinmedia/django-setup-configuration
Keywords: Django,Configuration
Classifier: Development Status :: 3 - Alpha
Classifier: Framework :: Django
Classifier: Framework :: Django :: 3.2
Classifier: Framework :: Django :: 4.2
Classifier: Framework :: Django :: 5.1
Classifier: Intended Audience :: Developers
Classifier: Operating System :: Unix
Classifier: Operating System :: MacOS
Classifier: Operating System :: Microsoft :: Windows
Classifier: Programming Language :: Python :: 3.10
Classifier: Programming Language :: Python :: 3.11
Classifier: Programming Language :: Python :: 3.12
Classifier: Topic :: Software Development :: Libraries :: Python Modules
Requires-Python: >=3.10
License-File: LICENSE
Requires-Dist: django>=3.2
Requires-Dist: pydantic>=2
Requires-Dist: pydantic-settings[yaml]>=2.2
Requires-Dist: ruamel.yaml>=0.18.10
Requires-Dist: docutils
Provides-Extra: tests
Requires-Dist: psycopg2; extra == "tests"
Requires-Dist: pytest; extra == "tests"
Requires-Dist: pytest-django; extra == "tests"
Requires-Dist: pytest-mock; extra == "tests"
Requires-Dist: furl; extra == "tests"
Requires-Dist: tox; extra == "tests"
Requires-Dist: isort; extra == "tests"
Requires-Dist: black; extra == "tests"
Requires-Dist: flake8; extra == "tests"
Requires-Dist: sphinx<=8.1.3; extra == "tests"
Requires-Dist: beautifulsoup4; extra == "tests"
Requires-Dist: approvaltests; extra == "tests"
Provides-Extra: coverage
Requires-Dist: pytest-cov; extra == "coverage"
Provides-Extra: docs
Requires-Dist: sphinx; extra == "docs"
Requires-Dist: sphinx-rtd-theme; extra == "docs"
Provides-Extra: release
Requires-Dist: bump-my-version; extra == "release"
Requires-Dist: twine; extra == "release"
Dynamic: license-file
